container_magic/__init__.py
container_magic/cli/__init__.py
container_magic/cli/main.py
container_magic/core/__init__.py
container_magic/core/cache.py
container_magic/core/config.py
container_magic/core/runtime.py
container_magic/core/templates.py
container_magic/generators/__init__.py
container_magic/generators/build_script.py
container_magic/generators/dockerfile.py
container_magic/generators/justfile.py
container_magic/generators/run_script.py
container_magic/generators/standalone_commands.py
container_magic/templates/Dockerfile.j2
container_magic/templates/Justfile.j2
container_magic/templates/build.sh.j2
container_magic/templates/custom_command.j2
container_magic/templates/run.sh.j2
container_magic/templates/standalone_command.sh.j2
container_magic-1.5.1.dist-info/licenses/LICENSE
container_magic-1.5.1.dist-info/METADATA
container_magic-1.5.1.dist-info/WHEEL
container_magic-1.5.1.dist-info/entry_points.txt
container_magic-1.5.1.dist-info/top_level.txt
container_magic-1.5.1.dist-info/RECORD
