Metadata-Version: 2.4
Name: container-magic
Version: 1.5.1
Summary: A tool for rapidly creating containerised development environments
Author-email: Mark Hedley Jones <mark@hedleyjones.com>
License: MIT
Project-URL: Homepage, https://github.com/markhedleyjones/container-magic
Project-URL: Repository, https://github.com/markhedleyjones/container-magic
Project-URL: Issues, https://github.com/markhedleyjones/container-magic/issues
Classifier: Development Status :: 3 - Alpha
Classifier: Intended Audience :: Developers
Classifier: License :: OSI Approved :: MIT License
Classifier: Programming Language :: Python :: 3
Classifier: Programming Language :: Python :: 3.8
Classifier: Programming Language :: Python :: 3.9
Classifier: Programming Language :: Python :: 3.10
Classifier: Programming Language :: Python :: 3.11
Classifier: Programming Language :: Python :: 3.12
Requires-Python: >=3.8
License-File: LICENSE
Requires-Dist: pyyaml>=6.0
Requires-Dist: jinja2>=3.1.0
Requires-Dist: click>=8.1.0
Requires-Dist: pydantic>=2.0.0
Requires-Dist: requests>=2.31.0
Provides-Extra: dev
Requires-Dist: pytest>=7.0.0; extra == "dev"
Requires-Dist: pytest-cov>=4.0.0; extra == "dev"
Requires-Dist: black>=23.0.0; extra == "dev"
Requires-Dist: ruff>=0.1.0; extra == "dev"
Requires-Dist: python-semantic-release>=8.0.0; extra == "dev"
Dynamic: license-file
